{"nodes": [{"id": "library", "label": "library.py", "file_type": "code", "source_file": "scrivai/cli/library.py", "source_location": "L1"}, {"id": "library_resolve_qmd_db", "label": "_resolve_qmd_db()", "file_type": "code", "source_file": "scrivai/cli/library.py", "source_location": "L14"}, {"id": "library_pick_library", "label": "_pick_library()", "file_type": "code", "source_file": "scrivai/cli/library.py", "source_location": "L21"}, {"id": "library_entry_to_json", "label": "_entry_to_json()", "file_type": "code", "source_file": "scrivai/cli/library.py", "source_location": "L26"}, {"id": "library_search_result_to_json", "label": "_search_result_to_json()", "file_type": "code", "source_file": "scrivai/cli/library.py", "source_location": "L34"}, {"id": "library_cmd_search", "label": "cmd_search()", "file_type": "code", "source_file": "scrivai/cli/library.py", "source_location": "L43"}, {"id": "library_cmd_get", "label": "cmd_get()", "file_type": "code", "source_file": "scrivai/cli/library.py", "source_location": "L53"}, {"id": "library_cmd_list", "label": "cmd_list()", "file_type": "code", "source_file": "scrivai/cli/library.py", "source_location": "L64"}, {"id": "library_register", "label": "register()", "file_type": "code", "source_file": "scrivai/cli/library.py", "source_location": "L72"}, {"id": "library_rationale_1", "label": "scrivai-cli library group \u2014 search / get / list\u3002", "file_type": "rationale", "source_file": "scrivai/cli/library.py", "source_location": "L1"}, {"id": "library_rationale_35", "label": "SearchResult \u900f\u4f20\u6240\u6709\u516c\u5f00\u5c5e\u6027(qmd \u63d0\u4f9b model_dump \u6216 dict)\u3002", "file_type": "rationale", "source_file": "scrivai/cli/library.py", "source_location": "L35"}], "edges": [{"source": "library", "target": "argparse", "relation": "imports", "confidence": "EXTRACTED", "source_file": "scrivai/cli/library.py", "source_location": "L5", "weight": 1.0}, {"source": "library", "target": "json", "relation": "imports", "confidence": "EXTRACTED", "source_file": "scrivai/cli/library.py", "source_location": "L6", "weight": 1.0}, {"source": "library", "target": "os", "relation": "imports", "confidence": "EXTRACTED", "source_file": "scrivai/cli/library.py", "source_location": "L7", "weight": 1.0}, {"source": "library", "target": "pathlib", "relation": "imports_from", "confidence": "EXTRACTED", "source_file": "scrivai/cli/library.py", "source_location": "L8", "weight": 1.0}, {"source": "library", "target": "typing", "relation": "imports_from", "confidence": "EXTRACTED", "source_file": "scrivai/cli/library.py", "source_location": "L9", "weight": 1.0}, {"source": "library", "target": "scrivai_knowledge", "relation": "imports_from", "confidence": "EXTRACTED", "source_file": "scrivai/cli/library.py", "source_location": "L11", "weight": 1.0}, {"source": "library", "target": "library_resolve_qmd_db", "relation": "contains", "confidence": "EXTRACTED", "source_file": "scrivai/cli/library.py", "source_location": "L14", "weight": 1.0}, {"source": "library", "target": "library_pick_library", "relation": "contains", "confidence": "EXTRACTED", "source_file": "scrivai/cli/library.py", "source_location": "L21", "weight": 1.0}, {"source": "library", "target": "library_entry_to_json", "relation": "contains", "confidence": "EXTRACTED", "source_file": "scrivai/cli/library.py", "source_location": "L26", "weight": 1.0}, {"source": "library", "target": "library_search_result_to_json", "relation": "contains", "confidence": "EXTRACTED", "source_file": "scrivai/cli/library.py", "source_location": "L34", "weight": 1.0}, {"source": "library", "target": "library_cmd_search", "relation": "contains", "confidence": "EXTRACTED", "source_file": "scrivai/cli/library.py", "source_location": "L43", "weight": 1.0}, {"source": "library", "target": "library_cmd_get", "relation": "contains", "confidence": "EXTRACTED", "source_file": "scrivai/cli/library.py", "source_location": "L53", "weight": 1.0}, {"source": "library", "target": "library_cmd_list", "relation": "contains", "confidence": "EXTRACTED", "source_file": "scrivai/cli/library.py", "source_location": "L64", "weight": 1.0}, {"source": "library", "target": "library_register", "relation": "contains", "confidence": "EXTRACTED", "source_file": "scrivai/cli/library.py", "source_location": "L72", "weight": 1.0}, {"source": "library_cmd_search", "target": "library_resolve_qmd_db", "relation": "calls", "confidence": "INFERRED", "source_file": "scrivai/cli/library.py", "source_location": "L44", "weight": 0.8}, {"source": "library_cmd_search", "target": "library_pick_library", "relation": "calls", "confidence": "INFERRED", "source_file": "scrivai/cli/library.py", "source_location": "L46", "weight": 0.8}, {"source": "library_cmd_search", "target": "library_search_result_to_json", "relation": "calls", "confidence": "INFERRED", "source_file": "scrivai/cli/library.py", "source_location": "L50", "weight": 0.8}, {"source": "library_cmd_get", "target": "library_resolve_qmd_db", "relation": "calls", "confidence": "INFERRED", "source_file": "scrivai/cli/library.py", "source_location": "L54", "weight": 0.8}, {"source": "library_cmd_get", "target": "library_pick_library", "relation": "calls", "confidence": "INFERRED", "source_file": "scrivai/cli/library.py", "source_location": "L56", "weight": 0.8}, {"source": "library_cmd_get", "target": "library_entry_to_json", "relation": "calls", "confidence": "INFERRED", "source_file": "scrivai/cli/library.py", "source_location": "L61", "weight": 0.8}, {"source": "library_cmd_list", "target": "library_resolve_qmd_db", "relation": "calls", "confidence": "INFERRED", "source_file": "scrivai/cli/library.py", "source_location": "L65", "weight": 0.8}, {"source": "library_cmd_list", "target": "library_pick_library", "relation": "calls", "confidence": "INFERRED", "source_file": "scrivai/cli/library.py", "source_location": "L67", "weight": 0.8}, {"source": "library_rationale_1", "target": "library", "relation": "rationale_for", "confidence": "EXTRACTED", "source_file": "scrivai/cli/library.py", "source_location": "L1", "weight": 1.0}, {"source": "library_rationale_35", "target": "library_search_result_to_json", "relation": "rationale_for", "confidence": "EXTRACTED", "source_file": "scrivai/cli/library.py", "source_location": "L35", "weight": 1.0}]}